[
 {
  "BUILDING_SLUG": "birthday_cake",
  "REQUIRED_BUILDING_LEVEL": 1,
  "REQUIRED_BUILDING_SLUG": "command_center",
  "max_count": 3
 },
 {
  "BUILDING_SLUG": "mushroom",
  "REQUIRED_BUILDING_LEVEL": 1,
  "REQUIRED_BUILDING_SLUG": "command_center",
  "max_count": 2
 },
 {
  "BUILDING_SLUG": "christmas_elka",
  "REQUIRED_BUILDING_LEVEL": 1,
  "REQUIRED_BUILDING_SLUG": "command_center",
  "max_count": 2
 },
 {
  "BUILDING_SLUG": "rip",
  "REQUIRED_BUILDING_LEVEL": 1,
  "REQUIRED_BUILDING_SLUG": "command_center",
  "max_count": 2
 },
 {
  "BUILDING_SLUG": "scarecrow",
  "REQUIRED_BUILDING_LEVEL": 1,
  "REQUIRED_BUILDING_SLUG": "command_center",
  "max_count": 2
 },
 {
  "BUILDING_SLUG": "stone_lego",
  "REQUIRED_BUILDING_LEVEL": 1,
  "REQUIRED_BUILDING_SLUG": "command_center",
  "max_count": 10
 },
 {
  "BUILDING_SLUG": "christmas_gift",
  "REQUIRED_BUILDING_LEVEL": 1,
  "REQUIRED_BUILDING_SLUG": "command_center",
  "max_count": 3
 },
 {
  "BUILDING_SLUG": "christmas_snowman",
  "REQUIRED_BUILDING_LEVEL": 1,
  "REQUIRED_BUILDING_SLUG": "command_center",
  "max_count": 1
 },
 {
  "BUILDING_SLUG": "zeus",
  "REQUIRED_BUILDING_LEVEL": 1,
  "REQUIRED_BUILDING_SLUG": "command_center",
  "max_count": 1
 },
 {
  "BUILDING_SLUG": "rocket_stone",
  "REQUIRED_BUILDING_LEVEL": 1,
  "REQUIRED_BUILDING_SLUG": "command_center",
  "max_count": 2
 },
 {
  "BUILDING_SLUG": "ufo",
  "REQUIRED_BUILDING_LEVEL": 1,
  "REQUIRED_BUILDING_SLUG": "command_center",
  "max_count": 2
 },
 {
  "BUILDING_SLUG": "flag_stock",
  "REQUIRED_BUILDING_LEVEL": 1,
  "REQUIRED_BUILDING_SLUG": "command_center",
  "max_count": 1
 },
 {
  "BUILDING_SLUG": "golden_cat",
  "REQUIRED_BUILDING_LEVEL": 1,
  "REQUIRED_BUILDING_SLUG": "command_center",
  "max_count": 1
 },
 {
  "BUILDING_SLUG": "dragon_bones",
  "REQUIRED_BUILDING_LEVEL": 1,
  "REQUIRED_BUILDING_SLUG": "command_center",
  "max_count": 1
 }
]